setup.py
poly/__init__.py
poly/polynomial.py
simple_polymath.egg-info/PKG-INFO
simple_polymath.egg-info/SOURCES.txt
simple_polymath.egg-info/dependency_links.txt
simple_polymath.egg-info/not-zip-safe
simple_polymath.egg-info/top_level.txt