Metadata-Version: 1.0
Name: simple-polymath
Version: 0.1
Summary: evaluation, and basic calculus of polynomials
Home-page: UNKNOWN
Author: Zafar Saifi
Author-email: fake@gmail.com
License: UNKNOWN
Platform: UNKNOWN
